clients/__init__.py
clients/asset_lake/__init__.py
clients/asset_lake/api/__init__.py
clients/asset_lake/api/assets_api.py
clients/asset_lake/api/default_api.py
clients/asset_lake/api_client.py
clients/asset_lake/api_response.py
clients/asset_lake/configuration.py
clients/asset_lake/exceptions.py
clients/asset_lake/models/__init__.py
clients/asset_lake/models/archiver_volume_storage_ref.py
clients/asset_lake/models/asset.py
clients/asset_lake/models/asset_type.py
clients/asset_lake/models/base_engine.py
clients/asset_lake/models/checkpoint_data.py
clients/asset_lake/models/complete_asset_upload_request.py
clients/asset_lake/models/complete_asset_upload_response.py
clients/asset_lake/models/create_asset_request.py
clients/asset_lake/models/create_asset_response.py
clients/asset_lake/models/data.py
clients/asset_lake/models/data_type.py
clients/asset_lake/models/delete_asset_response.py
clients/asset_lake/models/file_data.py
clients/asset_lake/models/file_extension.py
clients/asset_lake/models/file_format.py
clients/asset_lake/models/file_structure.py
clients/asset_lake/models/http_validation_error.py
clients/asset_lake/models/latent_data.py
clients/asset_lake/models/list_assets_response.py
clients/asset_lake/models/location_inner.py
clients/asset_lake/models/lora_data.py
clients/asset_lake/models/no_transfer_api.py
clients/asset_lake/models/presigned_url_transfer_api.py
clients/asset_lake/models/retrieve_asset_response.py
clients/asset_lake/models/status.py
clients/asset_lake/models/storage_descriptor.py
clients/asset_lake/models/sts_transfer_api.py
clients/asset_lake/models/textual_inversion_data.py
clients/asset_lake/models/transfer_api.py
clients/asset_lake/models/transfer_api1.py
clients/asset_lake/models/transfer_api_type.py
clients/asset_lake/models/vae_data.py
clients/asset_lake/models/validation_error.py
clients/asset_lake/models/volume_data.py
clients/asset_lake/rest.py
clients/fine_tuning/__init__.py
clients/fine_tuning/api/__init__.py
octoai_sdk-0.10.0.dist-info/METADATA
octoai_sdk-0.10.0.dist-info/WHEEL
octoai_sdk-0.10.0.dist-info/RECORD
